README
setup.py
apnsagent/__init__.py
apnsagent/apnsclient.py
apnsclient.egg-info/PKG-INFO
apnsclient.egg-info/SOURCES.txt
apnsclient.egg-info/dependency_links.txt
apnsclient.egg-info/top_level.txt