Metadata-Version: 1.0
Name: apnsclient
Version: 0.1
Summary: APNSagent Python client
Home-page: UNKNOWN
Author: jeff kit
Author-email: bbmyth@gmail.com
License: UNKNOWN
Platform: UNKNOWN
